shrt62/__init__.py
shrt62/hash.py
shrt62-0.2.0.dist-info/METADATA
shrt62-0.2.0.dist-info/WHEEL
shrt62-0.2.0.dist-info/top_level.txt
shrt62-0.2.0.dist-info/RECORD
