Metadata-Version: 2.4
Name: shrt62
Version: 0.2.0
Summary: shrt62 is a fast, easy-to-use Python package for creating short, unique IDs with hashing and Base62 encoding. Ideal for URL shorteners, link tracking, and any task needing compact identifiers.
Author-email: Mustapha Oyebamiji <mmusoye@gmail.com>
License: MIT
Requires-Dist: pytz
